Metadata-Version: 1.0
Name: duels-api
Version: 1.8
Summary: Wrapper for API
Home-page: https://github.com/Forevka69/DuelsGameBot
Author: Forevka
Author-email: zebestforevka@gmail.com
License: UNKNOWN
Platform: UNKNOWN
